<?xml version="1.0"?>
<projectProfile type="default" version="1.12.0">
  <projectDirectory>
    <projectProfileFile filesystemName=".zfproject.xml"/>
    <applicationDirectory classNamePrefix="Application_">
      <configsDirectory>
        <applicationConfigFile type="ini"/>
      </configsDirectory>
      <controllersDirectory>
        <controllerFile controllerName="Index">
          <actionMethod actionName="index"/>
          <actionMethod actionName="about"/>
          <actionMethod actionName="contact"/>
        </controllerFile>
        <controllerFile controllerName="Error"/>
        <controllerFile controllerName="Employee">
          <actionMethod actionName="index"/>
          <actionMethod actionName="post"/>
          <actionMethod actionName="put"/>
          <actionMethod actionName="delete"/>
        </controllerFile>
        <controllerFile controllerName="Toil">
          <actionMethod actionName="index"/>
          <actionMethod actionName="post"/>
          <actionMethod actionName="put"/>
          <actionMethod actionName="delete"/>
        </controllerFile>
      </controllersDirectory>
      <formsDirectory>
        <formFile formName="AddEmployee"/>
        <formFile formName="Toil"/>
      </formsDirectory>
      <layoutsDirectory>
        <layoutScriptsDirectory>
          <layoutScriptFile layoutName="layout"/>
        </layoutScriptsDirectory>
      </layoutsDirectory>
      <modelsDirectory>
        <dbTableDirectory>
          <dbTableFile dbTableName="Employees"/>
          <dbTableFile dbTableName="Toil"/>
          <dbTableFile dbTableName="Users"/>
        </dbTableDirectory>
        <modelFile modelName="Employee"/>
        <modelFile modelName="EmployeeMapper"/>
        <modelFile modelName="Toil"/>
        <modelFile modelName="ToilMapper"/>
        <modelFile modelName="UserMapper"/>
        <modelFile modelName="User"/>
      </modelsDirectory>
      <modulesDirectory>
        <moduleDirectory moduleName="App">
          <configsDirectory enabled="false"/>
          <controllersDirectory>
            <controllerFile controllerName="Credentials">
              <actionMethod actionName="index"/>
              <actionMethod actionName="changePassword"/>
              <actionMethod actionName="passwordChanged"/>
              <actionMethod actionName="reidentifyEmail"/>
            </controllerFile>
            <controllerFile controllerName="ForgotPassword">
              <actionMethod actionName="index"/>
              <actionMethod actionName="reidentifyEmail"/>
              <actionMethod actionName="confirmQuestions"/>
              <actionMethod actionName="confirmNotification"/>
            </controllerFile>
            <controllerFile controllerName="ChangePassword">
              <actionMethod actionName="index"/>
              <actionMethod actionName="changePassword"/>
              <actionMethod actionName="passwordChanged"/>
            </controllerFile>
          </controllersDirectory>
          <formsDirectory enabled="false">
            <formFile formName="ReidentifyEmail"/>
            <formFile formName="ConfirmQuestions"/>
          </formsDirectory>
          <layoutsDirectory enabled="false">
            <layoutScriptsDirectory enabled="false"/>
          </layoutsDirectory>
          <modelsDirectory>
            <dbTableDirectory enabled="false"/>
          </modelsDirectory>
          <servicesDirectory enabled="false"/>
          <viewsDirectory>
            <viewScriptsDirectory>
              <viewControllerScriptsDirectory forControllerName="Credentials">
                <viewScriptFile forActionName="index"/>
              </viewControllerScriptsDirectory>
              <viewControllerScriptsDirectory forControllerName="Credentials">
                <viewScriptFile forActionName="changePassword"/>
              </viewControllerScriptsDirectory>
              <viewControllerScriptsDirectory forControllerName="Credentials">
                <viewScriptFile forActionName="passwordChanged"/>
              </viewControllerScriptsDirectory>
              <viewControllerScriptsDirectory forControllerName="Credentials">
                <viewScriptFile forActionName="reidentifyEmail"/>
              </viewControllerScriptsDirectory>
              <viewControllerScriptsDirectory forControllerName="ForgotPassword">
                <viewScriptFile forActionName="index"/>
              </viewControllerScriptsDirectory>
              <viewControllerScriptsDirectory forControllerName="ChangePassword">
                <viewScriptFile forActionName="index"/>
              </viewControllerScriptsDirectory>
              <viewControllerScriptsDirectory forControllerName="ChangePassword">
                <viewScriptFile forActionName="changePassword"/>
              </viewControllerScriptsDirectory>
              <viewControllerScriptsDirectory forControllerName="ChangePassword">
                <viewScriptFile forActionName="passwordChanged"/>
              </viewControllerScriptsDirectory>
              <viewControllerScriptsDirectory forControllerName="ForgotPassword">
                <viewScriptFile forActionName="reidentifyEmail"/>
              </viewControllerScriptsDirectory>
              <viewControllerScriptsDirectory forControllerName="ForgotPassword">
                <viewScriptFile forActionName="confirmQuestions"/>
              </viewControllerScriptsDirectory>
              <viewControllerScriptsDirectory forControllerName="ForgotPassword">
                <viewScriptFile forActionName="confirmNotification"/>
              </viewControllerScriptsDirectory>
            </viewScriptsDirectory>
            <viewHelpersDirectory/>
            <viewFiltersDirectory/>
          </viewsDirectory>
        </moduleDirectory>
      </modulesDirectory>
      <servicesDirectory enabled="false"/>
      <viewsDirectory>
        <viewScriptsDirectory>
          <viewControllerScriptsDirectory forControllerName="Index">
            <viewScriptFile forActionName="index"/>
          </viewControllerScriptsDirectory>
          <viewControllerScriptsDirectory forControllerName="Error">
            <viewScriptFile forActionName="error"/>
          </viewControllerScriptsDirectory>
          <viewControllerScriptsDirectory forControllerName="Employee">
            <viewScriptFile forActionName="index"/>
          </viewControllerScriptsDirectory>
          <viewControllerScriptsDirectory forControllerName="Employee">
            <viewScriptFile forActionName="post"/>
          </viewControllerScriptsDirectory>
          <viewControllerScriptsDirectory forControllerName="Employee">
            <viewScriptFile forActionName="put"/>
          </viewControllerScriptsDirectory>
          <viewControllerScriptsDirectory forControllerName="Employee">
            <viewScriptFile forActionName="delete"/>
          </viewControllerScriptsDirectory>
          <viewControllerScriptsDirectory forControllerName="Toil">
            <viewScriptFile forActionName="index"/>
          </viewControllerScriptsDirectory>
          <viewControllerScriptsDirectory forControllerName="Toil">
            <viewScriptFile forActionName="post"/>
          </viewControllerScriptsDirectory>
          <viewControllerScriptsDirectory forControllerName="Toil">
            <viewScriptFile forActionName="put"/>
          </viewControllerScriptsDirectory>
          <viewControllerScriptsDirectory forControllerName="Toil">
            <viewScriptFile forActionName="delete"/>
          </viewControllerScriptsDirectory>
          <viewControllerScriptsDirectory forControllerName="Index">
            <viewScriptFile forActionName="about"/>
          </viewControllerScriptsDirectory>
          <viewControllerScriptsDirectory forControllerName="Index">
            <viewScriptFile forActionName="contact"/>
          </viewControllerScriptsDirectory>
        </viewScriptsDirectory>
        <viewHelpersDirectory/>
        <viewFiltersDirectory enabled="false"/>
      </viewsDirectory>
      <bootstrapFile filesystemName="Bootstrap.php"/>
    </applicationDirectory>
    <dataDirectory enabled="false">
      <cacheDirectory enabled="false"/>
      <searchIndexesDirectory enabled="false"/>
      <localesDirectory enabled="false"/>
      <logsDirectory enabled="false"/>
      <sessionsDirectory enabled="false"/>
      <uploadsDirectory enabled="false"/>
    </dataDirectory>
    <docsDirectory>
      <file filesystemName="README.txt"/>
    </docsDirectory>
    <libraryDirectory>
      <zfStandardLibraryDirectory enabled="false"/>
    </libraryDirectory>
    <publicDirectory>
      <publicStylesheetsDirectory enabled="false"/>
      <publicScriptsDirectory enabled="false"/>
      <publicImagesDirectory enabled="false"/>
      <publicIndexFile filesystemName="index.php"/>
      <htaccessFile filesystemName=".htaccess"/>
    </publicDirectory>
    <projectProvidersDirectory enabled="false"/>
    <temporaryDirectory enabled="false"/>
    <testsDirectory>
      <testPHPUnitConfigFile filesystemName="phpunit.xml"/>
      <testPHPUnitBootstrapFile filesystemName="bootstrap.php"/>
      <testApplicationDirectory>
        <testApplicationControllerDirectory>
          <testApplicationControllerFile forControllerName="Index"/>
        </testApplicationControllerDirectory>
      </testApplicationDirectory>
      <testLibraryDirectory/>
    </testsDirectory>
  </projectDirectory>
</projectProfile>
